add_root_to_sys_path.py
add_root_to_sys_path-0.3.dist-info/LICENSE
add_root_to_sys_path-0.3.dist-info/WHEEL
add_root_to_sys_path-0.3.dist-info/METADATA
add_root_to_sys_path-0.3.dist-info/RECORD
